camera_ui_python_types/__init__.py
camera_ui_python_types/__init__.pyi
camera_ui_python_types/hybrid_observer.py
camera_ui_python_types/hybrid_observer.pyi
camera_ui_python_types/py.typed
camera_ui_python_types/test.py
camera_ui_python_types/test.pyi
camera_ui_python_types-0.2.20.dist-info/LICENSE.md
camera_ui_python_types-0.2.20.dist-info/METADATA
camera_ui_python_types-0.2.20.dist-info/WHEEL
camera_ui_python_types-0.2.20.dist-info/top_level.txt
camera_ui_python_types-0.2.20.dist-info/RECORD
